{
  "folder_id": "192wpg8KYF0gyhCyHpUtFUsrB9Gg-jiks",
  "modified_time": "2025-09-30T13:31:23.631Z",
  "cached_at": "2026-02-18T22:45:29.400386",
  "items": [
    {
      "id": "1PlhMp28DmZYTt5hBAttN1IAIpTxSZFhM",
      "name": "1. עבודת סוכות.pdf",
      "mimeType": "application/pdf"
    },
    {
      "id": "14V0AlJWrnSTqmlQ4XBLk7iWWQy_uVGLG",
      "name": "2. פתרון בגרות 2012 - קיץ מועד א - גאומטריה.pdf",
      "mimeType": "application/pdf"
    },
    {
      "id": "1__9cleexOTj2WLdcrJzLNocc1jzj3xat",
      "name": "3. פתרון בגרות 2012 - קיץ מועד א - טריגו.pdf",
      "mimeType": "application/pdf"
    },
    {
      "id": "14RuXskF_NqrL-qeWvMx_ymuuMGkprcu0",
      "name": "4. פתרון בגרות חורף 2016 - טריגו.pdf",
      "mimeType": "application/pdf"
    },
    {
      "id": "1pity5gL8wPnlzjLSY_LEgHung57jf8YE",
      "name": "5. פתרון בגרות קיץ 2014 מועד ב - טריגו.pdf",
      "mimeType": "application/pdf"
    }
  ]
}