{
  "folder_id": "1o5frG6CZo9ir7I9G6s5lP1hdhAguGnHm",
  "modified_time": "2025-11-19T18:14:32.256Z",
  "cached_at": "2026-02-18T22:44:58.182368",
  "items": [
    {
      "id": "1xh0NPNHBNXxlIuwggpQWb3qRSdoOxhqo",
      "name": "1. סיכום שיעור.pdf",
      "mimeType": "application/pdf"
    },
    {
      "id": "1iDRu2n7sY2oAbg7elq_1Px3iuHE6pZRi",
      "name": "2. סיכום שיעור - תוספת - טרנספורמציות.pdf",
      "mimeType": "application/pdf"
    },
    {
      "id": "16EII9MUA_NXF3dq_kmBAut06mLU3IotV",
      "name": "3. ש.ב קדם אנליזה.pdf",
      "mimeType": "application/pdf"
    },
    {
      "id": "1KEhJCmZMK16cYwifZkTWDgyRtDMIZ1zl",
      "name": "4. ש.ב נגזרות.pdf",
      "mimeType": "application/pdf"
    },
    {
      "id": "1Xre3YhP-yfe10pl8iYUc4Zhs3mtVYKNB",
      "name": "5. סרטון המחשה סינוס.gif",
      "mimeType": "image/gif"
    },
    {
      "id": "1meTdRPWSEkN8RU7BEYzWtp65BZViNm1-",
      "name": "README.md",
      "mimeType": "text/markdown"
    }
  ]
}